brnltk/__init__.py
brnltk/dialect_translator.py
brnltk/pos_tagger.py
brnltk/similarity_checker.py
brnltk/stemmer.py
brnltk/tokenizer.py
brposNLTK/__init__.py
brposNLTK/dialect_translator.py
brposNLTK/pos_tagger.py
brnltk-3.2.2.dist-info/METADATA
brnltk-3.2.2.dist-info/WHEEL
brnltk-3.2.2.dist-info/top_level.txt
brnltk-3.2.2.dist-info/RECORD
