Metadata-Version: 2.4
Name: brnltk
Version: 3.2.2
Summary: A Part-of-Speech Tagger and Dialect Processing Toolkit for Bengali.
Home-page: https://github.com/ShakirHaque/brposNLTK
Author: Mahmudul Haque Shakir
Author-email: mahmudulhaqueshakir@gmail.com
Classifier: Programming Language :: Python :: 3
Classifier: License :: OSI Approved :: MIT License
Classifier: Operating System :: OS Independent
Classifier: Intended Audience :: Developers
Classifier: Intended Audience :: Science/Research
Classifier: Topic :: Text Processing :: Linguistic
Classifier: Natural Language :: Bengali
Requires-Python: >=3.6
Requires-Dist: pandas>=1.3.0
Requires-Dist: numpy>=1.21.0
Requires-Dist: tensorflow>=2.10.0
Requires-Dist: openpyxl>=3.0.0
Provides-Extra: dev
Requires-Dist: keras>=2.12.0; extra == "dev"
Requires-Dist: scikit-learn>=1.2.0; extra == "dev"
Provides-Extra: testing
Requires-Dist: pytest>=7.0.0; extra == "testing"
Dynamic: author
Dynamic: author-email
Dynamic: classifier
Dynamic: description
Dynamic: description-content-type
Dynamic: home-page
Dynamic: provides-extra
Dynamic: requires-dist
Dynamic: requires-python
Dynamic: summary
